{
  "themeIndex": 1,
  "sortMode": 0,
  "tasks": [
    {
      "id": 1769526170970377967,
      "title": "движение",
      "done": true,
      "dueAt": "0001-01-01T00:00:00Z",
      "notified": false
    },
    {
      "id": 1769526174441012102,
      "title": "враги",
      "done": false,
      "dueAt": "0001-01-01T00:00:00Z",
      "notified": false
    },
    {
      "id": 1769526183759913886,
      "title": "пушки",
      "done": false,
      "dueAt": "0001-01-01T00:00:00Z",
      "notified": false
    },
    {
      "id": 1769526226536824538,
      "title": "интерактивные объекты без отталкивания",
      "done": false,
      "dueAt": "0001-01-01T00:00:00Z",
      "notified": false
    },
    {
      "id": 1771600463379415203,
      "title": "мимики",
      "done": false,
      "dueAt": "0001-01-01T00:00:00Z",
      "notified": false
    }
  ]
}